pca_tools/__init__.py
pca_tools/exceptions.py
pca_tools/functions.py
pca_tools/model.py
pca_tools/optimizer.py
pca_tools/utils.py
pca_tools-0.2.11.dist-info/LICENSE
pca_tools-0.2.11.dist-info/METADATA
pca_tools-0.2.11.dist-info/WHEEL
pca_tools-0.2.11.dist-info/top_level.txt
pca_tools-0.2.11.dist-info/RECORD
