Metadata-Version: 2.2
Name: pca_tools
Version: 0.2.11
Summary: PCA tools for data analysis
Home-page: https://github.com/Fidaeic/pca_tools
Author: Fidae El Morer
Author-email: elmorer.fidae@gmail.com
License: MIT
License-File: LICENSE
Requires-Dist: numpy
Requires-Dist: pandas
Requires-Dist: matplotlib
Requires-Dist: seaborn
Requires-Dist: scikit-learn
Requires-Dist: altair
Requires-Dist: statsmodels
Requires-Dist: scipy
Dynamic: author
Dynamic: author-email
Dynamic: description
Dynamic: description-content-type
Dynamic: home-page
Dynamic: license
Dynamic: requires-dist
Dynamic: summary
